eevend_libs-0.0.4-py3.7-nspkg.pth
eevend_libs/client/__init__.py
eevend_libs/client/base_client.py
eevend_libs/client/exceptions.py
eevend_libs/constants/__init__.py
eevend_libs/constants/http_codes.py
eevend_libs/flask_service_exceptions/__init__.py
eevend_libs/flask_service_exceptions/exceptions.py
eevend_libs/micro_lib_template/__init__.py
eevend_libs/micro_lib_template/micro_lib_template.py
eevend_libs/service/__init__.py
eevend_libs/service/service_config.py
eevend_libs/utils/__init__.py
eevend_libs/utils/formatters.py
eevend_libs-0.0.4.dist-info/LICENSE
eevend_libs-0.0.4.dist-info/METADATA
eevend_libs-0.0.4.dist-info/WHEEL
eevend_libs-0.0.4.dist-info/namespace_packages.txt
eevend_libs-0.0.4.dist-info/top_level.txt
eevend_libs-0.0.4.dist-info/RECORD
