Metadata-Version: 2.1
Name: eevend-libs
Version: 0.0.4
Summary: UNKNOWN
Author: EEVEND
Author-email: info.eevend@gmail.com
License: UNKNOWN
Platform: UNKNOWN
License-File: LICENSE
Requires-Dist: requests
Requires-Dist: future
Requires-Dist: getconf
Requires-Dist: srvlookup (>=3)
Requires-Dist: dnspython
Requires-Dist: python-version (>="3.0")
